rag_skeleton/__init__.py
rag_skeleton/__main__.py
rag_skeleton/data_processing.py
rag_skeleton/generation.py
rag_skeleton/rag.py
rag_skeleton/retrieval.py
rag_skeleton/run.py
rag_skeleton-0.1.3.dist-info/LICENSE.txt
rag_skeleton-0.1.3.dist-info/METADATA
rag_skeleton-0.1.3.dist-info/WHEEL
rag_skeleton-0.1.3.dist-info/entry_points.txt
rag_skeleton-0.1.3.dist-info/top_level.txt
rag_skeleton-0.1.3.dist-info/RECORD
