Metadata-Version: 2.1
Name: rag_skeleton
Version: 0.1.3
Summary: Add a short description here!
Home-page: https://github.com/hasan-sayeed/RAGSkeleton
Author: Hasan Muhammad Sayeed
Author-email: hasan.sayeed.71.93@gmail.com
License: MIT
Project-URL: Documentation, https://ragskeleton.readthedocs.io/en/latest/
Project-URL: Source, https://github.com/hasan-sayeed/RAGSkeleton
Project-URL: Tracker, https://github.com/hasan-sayeed/RAGSkeleton/issues
Platform: any
Classifier: Development Status :: 4 - Beta
Classifier: License :: OSI Approved :: MIT License
Classifier: Programming Language :: Python :: 3
Classifier: Programming Language :: Python :: 3.10
Classifier: Topic :: Scientific/Engineering
Requires-Python: >=3.10.15
License-File: LICENSE.txt
Requires-Dist: numpy
Requires-Dist: scipy==1.14.1
Requires-Dist: tqdm==4.67.0
Requires-Dist: click==8.1.7
Requires-Dist: langchain==0.3.7
Requires-Dist: langchain-community==0.3.5
Requires-Dist: langchain-chroma==0.1.4
Requires-Dist: langchain-huggingface==0.1.2
Requires-Dist: pymupdf==1.24.13
Requires-Dist: sentence-transformers==3.2.1
Provides-Extra: testing
Requires-Dist: setuptools; extra == "testing"
Requires-Dist: pytest; extra == "testing"
Requires-Dist: pytest-cov; extra == "testing"
